infcraft/__init__.py
infcraft-1.0.0.dist-info/METADATA
infcraft-1.0.0.dist-info/WHEEL
infcraft-1.0.0.dist-info/RECORD
