Metadata-Version: 2.4
Name: infcraft
Version: 1.0.0
Summary: A simple Python wrapper for the unofficial Infinite Craft API.
Project-URL: Homepage, https://mineogo.is-a.dev/
Project-URL: Bug Tracker, https://github.com/mineogo/infcraft/issues
Author-email: mineogo <venkatesh10year@gmail.com>
Classifier: Intended Audience :: Developers
Classifier: License :: OSI Approved :: MIT License
Classifier: Operating System :: OS Independent
Classifier: Programming Language :: Python :: 3
Classifier: Topic :: Games/Entertainment
Classifier: Topic :: Software Development :: Libraries :: Python Modules
Requires-Python: >=3.7
Requires-Dist: requests
